README.md
setup.py
subgal/__init__.py
subgal/host.py
subgal/make_indices.py
subgal/make_thumbs.py
subgal/subgal.py
subgal.egg-info/PKG-INFO
subgal.egg-info/SOURCES.txt
subgal.egg-info/dependency_links.txt
subgal.egg-info/entry_points.txt
subgal.egg-info/requires.txt
subgal.egg-info/top_level.txt
subgal/templates/individual_index_template.html