Metadata-Version: 1.0
Name: subgal
Version: 1.0.1
Summary: A collection of tools for creating html galleries from photos that have been sorted by sortphotos
Home-page: https://github.com/jbaber/subgal
Author: John Baber-Lucero
Author-email: pypi@frundle.com
License: GPLv3
Platform: UNKNOWN
